Metadata-Version: 2.1
Name: mnzipcode
Version: 0.1.21
Summary: mnzipcode is a simple library for querying Mongolian zip codes.
Home-page: https://github.com/bekkage/mnzipcode
Author: Bekkage
Author-email: bilguunsec@gmail.com
Keywords: mnzipcode zipcode mongolia mn zip code
